{
  "kind": "collectionType",
  "collectionName": "follows",
  "info": {
    "singularName": "follow",
    "pluralName": "follows",
    "displayName": "follow",
    "description": ""
  },
  "options": {
    "draftAndPublish": true
  },
  "pluginOptions": {},
  "attributes": {
    "follower_id": {
      "type": "integer"
    },
    "followed_at": {
      "type": "datetime"
    },
    "stores": {
      "type": "relation",
      "relation": "manyToMany",
      "target": "api::store.store",
      "inversedBy": "follows"
    }
  }
}
